<?xml version="1.0" encoding="utf-8"?>
<page id="7.xml">
  <bgimage>pic_7.jpg</bgimage>
  <text>Bodegas

Las bodegas, desangeladas y frías (¿a dónde habrá ido a parar la carga?), dan paso a dos compartimentos, uno abierto y el otro completamente cerrado por el óxido. Aunque empiezas a desconfiar de tus propios sentidos, vuelves a tener la sensación de ver a alguien -o algo- colándose por entre la puerta abierta..</text>
  <options>
    <option target="6.xml">Ascender a la segunda cubierta</option>
    <option target="8.xml">Entrar en la habitación</option>
  </options>
</page>
